bayesqp/__init__.py
bayesqp/bayesqp.py
bayesqp/configs.py
bayesqp/models.py
bayesqp/objective_wrappers.py
bayesqp/subproblems.py
bayesqp/utils.py
bayesqp-0.1.1.dist-info/METADATA
bayesqp-0.1.1.dist-info/WHEEL
bayesqp-0.1.1.dist-info/licenses/LICENSE
bayesqp-0.1.1.dist-info/RECORD
