Metadata-Version: 2.4
Name: bayesqp
Version: 0.1.1
Summary: BayeSQP: Bayesian Optimization through Sequential Quadratic Programming
Project-URL: Repository, https://github.com/brunzema/bayesqp
Author: Paul Brunzema
License: MIT License
License-File: LICENSE
Classifier: Development Status :: 3 - Alpha
Classifier: License :: OSI Approved :: MIT License
Classifier: Programming Language :: Python :: 3
Classifier: Programming Language :: Python :: 3.11
Requires-Python: >=3.11
Requires-Dist: botorch
Requires-Dist: cvxopt
Requires-Dist: gpytorch
Requires-Dist: numpy
Requires-Dist: scipy
Provides-Extra: examples
Requires-Dist: jupyter; extra == 'examples'
Requires-Dist: matplotlib; extra == 'examples'
